ExPSO/ExPSOClass.py
ExPSO/__init__.py
ExPSO-0.1.4.dist-info/LICENSE
ExPSO-0.1.4.dist-info/METADATA
ExPSO-0.1.4.dist-info/WHEEL
ExPSO-0.1.4.dist-info/top_level.txt
ExPSO-0.1.4.dist-info/RECORD
