Metadata-Version: 2.1
Name: ExPSO
Version: 0.1.4
Summary: The Exponential Particle Swarm Optimization (ExPSO) is a Python library that implements an extended variant of the Particle Swarm Optimization (PSO) algorithm. 
Author-email: Insaf Kraidia <insaf.kraidia@univ-constantine2.dz>, Khelil Kassoul <khelil.kassoul@etu.unige.ch>, Samir Brahim Belhaouari <sbelhaouari@hbku.edu.qa>, Naoufel Cheikhrouhou <naoufel.cheikhrouhou@hesge.ch>, Nicolas Zufferey <nicolas.zufferey.1@ulaval.ca>
Project-URL: Homepage, https://github.com/insafkraidia/ExPSO.git
Project-URL: Bug Tracker, https://github.com/insafkraidia/ExPSO.git
Classifier: Programming Language :: Python :: 3
Classifier: License :: OSI Approved :: MIT License
Classifier: Operating System :: OS Independent
Requires-Python: >=3.7
License-File: LICENSE
